Workbook

Sheet Inputs
A1: Usage-based pricing - TMS only (AI Dispatcher parked). Yellow = editable.
A3: Pricing model 1: graduated price per DELIVERED load
A4: Band 1 size (loads) | B4: 100
A5: Band 1 price per load | B5: 1
A6: Band 2 size (loads) | B6: 400
A7: Band 2 price per load | B7: 0.75
A8: Band 3 size (loads) | B8: 1500
A9: Band 3 price per load | B9: 0.55
A10: Band 4 price per load (above bands 1-3) | B10: 0.4
A11: Monthly minimum (all models) | B11: 19
A12: Pricing model 2: per ACTIVE truck (>=1 load in month)
A13: Price per active truck per month | B13: 14
A14: Pricing model 3: hybrid
A15: Hybrid price per active truck | B15: 5
A16: Hybrid price per delivered load | B16: 0.45
A17: Cost assumptions (non-AI TMS)
A18: Variable cost per delivered load (SMS, email, doc parse/OCR, maps, storage) [estimate] | B18: 0.08
A19: Variable cost per active truck per month (DVIR AI photos, ELD sync, storage) [estimate] | B19: 1
A20: Payment processing % of revenue (Stripe blended) [3P] | B20: 0.025
A21: Payment processing fixed per month | B21: 0.3
A22: Competitor reference: Alvys $/load (Abdel's own: ~$1,500/mo at ~3,000 loads) | B22: 0.5

Sheet Pricing_Comparison
A1: Monthly price, effective $/load and gross margin by pricing model
A3: Line | B3: Owner-operator (1 truck) | C3: Small fleet (5 trucks) | D3: 10 trucks | E3: ANH today (~23 trucks, ~295 loads) | F3: 25 trucks (4 loads/wk) | G3: 100 trucks (4 loads/wk) | H3: ANH Alvys era (~95 trucks, ~3,000 loads)
A4: Active trucks | B4: 1 | C4: 5 | D4: 10 | E4: 23 | F4: 25 | G4: 100 | H4: 95
A5: Delivered loads / month | B5: 17.3 | C5: 86.6 | D5: 173.2 | E5: 295 | F5: 433 | G5: 1732 | H5: 3000
A6: Support+success allocation $/mo [placeholder] | B6: 3 | C6: 8 | D6: 15 | E6: 75 | F6: 80 | G6: 400 | H6: 400
A7: Infra share $/mo [placeholder] | B7: 1 | C7: 6 | D7: 6 | E7: 12 | F7: 12 | G7: 40 | H7: 40
A8: Variable cost $/mo | B8: =B5*Inputs!$B$18+B4*Inputs!$B$19 -> 2.384 | C8: =C5*Inputs!$B$18+C4*Inputs!$B$19 -> 11.928 | D8: =D5*Inputs!$B$18+D4*Inputs!$B$19 -> 23.856 | E8: =E5*Inputs!$B$18+E4*Inputs!$B$19 -> 46.6 | F8: =F5*Inputs!$B$18+F4*Inputs!$B$19 -> 59.64 | G8: =G5*Inputs!$B$18+G4*Inputs!$B$19 -> 238.56 | H8: =H5*Inputs!$B$18+H4*Inputs!$B$19 -> 335
A9: M1 PRICE per delivered load (graduated) | B9: =MAX(Inputs!$B$11,Inputs!$B$5*MIN(B5,Inputs!$B$4)+Inputs!$B$7*MAX(0,MIN(B5,Inputs!$B$4+Inputs!$B$6)-Inputs!$B$4)+Inputs!$B$9*MAX(0,MIN(B5,Inputs!$B$4+Inputs!$B$6+Inputs!$B$8)-Inputs!$B$4-Inputs!$B$6)+Inputs!$B$10*MAX(0,B5-Inputs!$B$4-Inputs!$B$6-Inputs!$B$8)) -> 19 | C9: =MAX(Inputs!$B$11,Inputs!$B$5*MIN(C5,Inputs!$B$4)+Inputs!$B$7*MAX(0,MIN(C5,Inputs!$B$4+Inputs!$B$6)-Inputs!$B$4)+Inputs!$B$9*MAX(0,MIN(C5,Inputs!$B$4+Inputs!$B$6+Inputs!$B$8)-Inputs!$B$4-Inputs!$B$6)+Inputs!$B$10*MAX(0,C5-Inputs!$B$4-Inputs!$B$6-Inputs!$B$8)) -> 86.6 | D9: =MAX(Inputs!$B$11,Inputs!$B$5*MIN(D5,Inputs!$B$4)+Inputs!$B$7*MAX(0,MIN(D5,Inputs!$B$4+Inputs!$B$6)-Inputs!$B$4)+Inputs!$B$9*MAX(0,MIN(D5,Inputs!$B$4+Inputs!$B$6+Inputs!$B$8)-Inputs!$B$4-Inputs!$B$6)+Inputs!$B$10*MAX(0,D5-Inputs!$B$4-Inputs!$B$6-Inputs!$B$8)) -> 154.9 | E9: =MAX(Inputs!$B$11,Inputs!$B$5*MIN(E5,Inputs!$B$4)+Inputs!$B$7*MAX(0,MIN(E5,Inputs!$B$4+Inputs!$B$6)-Inputs!$B$4)+Inputs!$B$9*MAX(0,MIN(E5,Inputs!$B$4+Inputs!$B$6+Inputs!$B$8)-Inputs!$B$4-Inputs!$B$6)+Inputs!$B$10*MAX(0,E5-Inputs!$B$4-Inputs!$B$6-Inputs!$B$8)) -> 246.25 | F9: =MAX(Inputs!$B$11,Inputs!$B$5*MIN(F5,Inputs!$B$4)+Inputs!$B$7*MAX(0,MIN(F5,Inputs!$B$4+Inputs!$B$6)-Inputs!$B$4)+Inputs!$B$9*MAX(0,MIN(F5,Inputs!$B$4+Inputs!$B$6+Inputs!$B$8)-Inputs!$B$4-Inputs!$B$6)+Inputs!$B$10*MAX(0,F5-Inputs!$B$4-Inputs!$B$6-Inputs!$B$8)) -> 349.75 | G9: =MAX(Inputs!$B$11,Inputs!$B$5*MIN(G5,Inputs!$B$4)+Inputs!$B$7*MAX(0,MIN(G5,Inputs!$B$4+Inputs!$B$6)-Inputs!$B$4)+Inputs!$B$9*MAX(0,MIN(G5,Inputs!$B$4+Inputs!$B$6+Inputs!$B$8)-Inputs!$B$4-Inputs!$B$6)+Inputs!$B$10*MAX(0,G5-Inputs!$B$4-Inputs!$B$6-Inputs!$B$8)) -> 1077.6 | H9: =MAX(Inputs!$B$11,Inputs!$B$5*MIN(H5,Inputs!$B$4)+Inputs!$B$7*MAX(0,MIN(H5,Inputs!$B$4+Inputs!$B$6)-Inputs!$B$4)+Inputs!$B$9*MAX(0,MIN(H5,Inputs!$B$4+Inputs!$B$6+Inputs!$B$8)-Inputs!$B$4-Inputs!$B$6)+Inputs!$B$10*MAX(0,H5-Inputs!$B$4-Inputs!$B$6-Inputs!$B$8)) -> 1625
A10: M1 effective $/load | B10: =B9/B5 -> 1.0982659 | C10: =C9/C5 -> 1 | D10: =D9/D5 -> 0.8943418 | E10: =E9/E5 -> 0.83474576 | F10: =F9/F5 -> 0.80773672 | G10: =G9/G5 -> 0.6221709 | H10: =H9/H5 -> 0.54166667
A11: M1 gross margin | B11: =(B9-(B8+B6+B7)-(Inputs!$B$20*B9+Inputs!$B$21))/B9 -> 0.62321053 | C11: =(C9-(C8+C6+C7)-(Inputs!$B$20*C9+Inputs!$B$21))/C9 -> 0.67213626 | D11: =(D9-(D8+D6+D7)-(Inputs!$B$20*D9+Inputs!$B$21))/D9 -> 0.68348289 | E11: =(E9-(E8+E6+E7)-(Inputs!$B$20*E9+Inputs!$B$21))/E9 -> 0.43124365 | F11: =(F9-(F8+F6+F7)-(Inputs!$B$20*F9+Inputs!$B$21))/F9 -> 0.54057541 | G11: =(G9-(G8+G6+G7)-(Inputs!$B$20*G9+Inputs!$B$21))/G9 -> 0.34502598 | H11: =(H9-(H8+H6+H7)-(Inputs!$B$20*H9+Inputs!$B$21))/H9 -> 0.49789231
A12: M2 PRICE per active truck | B12: =MAX(Inputs!$B$11,Inputs!$B$13*B4) -> 19 | C12: =MAX(Inputs!$B$11,Inputs!$B$13*C4) -> 70 | D12: =MAX(Inputs!$B$11,Inputs!$B$13*D4) -> 140 | E12: =MAX(Inputs!$B$11,Inputs!$B$13*E4) -> 322 | F12: =MAX(Inputs!$B$11,Inputs!$B$13*F4) -> 350 | G12: =MAX(Inputs!$B$11,Inputs!$B$13*G4) -> 1400 | H12: =MAX(Inputs!$B$11,Inputs!$B$13*H4) -> 1330
A13: M2 effective $/load | B13: =B12/B5 -> 1.0982659 | C13: =C12/C5 -> 0.80831409 | D13: =D12/D5 -> 0.80831409 | E13: =E12/E5 -> 1.0915254 | F13: =F12/F5 -> 0.80831409 | G13: =G12/G5 -> 0.80831409 | H13: =H12/H5 -> 0.44333333
A14: M2 gross margin | B14: =(B12-(B8+B6+B7)-(Inputs!$B$20*B12+Inputs!$B$21))/B12 -> 0.62321053 | C14: =(C12-(C8+C6+C7)-(Inputs!$B$20*C12+Inputs!$B$21))/C12 -> 0.60031429 | D14: =(D12-(D8+D6+D7)-(Inputs!$B$20*D12+Inputs!$B$21))/D12 -> 0.65245714 | E14: =(E12-(E8+E6+E7)-(Inputs!$B$20*E12+Inputs!$B$21))/E12 -> 0.55916149 | F14: =(F12-(F8+F6+F7)-(Inputs!$B$20*F12+Inputs!$B$21))/F12 -> 0.54088571 | G14: =(G12-(G8+G6+G7)-(Inputs!$B$20*G12+Inputs!$B$21))/G12 -> 0.4901 | H14: =(H12-(H8+H6+H7)-(Inputs!$B$20*H12+Inputs!$B$21))/H12 -> 0.39206767
A15: M3 PRICE hybrid truck + load | B15: =MAX(Inputs!$B$11,Inputs!$B$15*B4+Inputs!$B$16*B5) -> 19 | C15: =MAX(Inputs!$B$11,Inputs!$B$15*C4+Inputs!$B$16*C5) -> 63.97 | D15: =MAX(Inputs!$B$11,Inputs!$B$15*D4+Inputs!$B$16*D5) -> 127.94 | E15: =MAX(Inputs!$B$11,Inputs!$B$15*E4+Inputs!$B$16*E5) -> 247.75 | F15: =MAX(Inputs!$B$11,Inputs!$B$15*F4+Inputs!$B$16*F5) -> 319.85 | G15: =MAX(Inputs!$B$11,Inputs!$B$15*G4+Inputs!$B$16*G5) -> 1279.4 | H15: =MAX(Inputs!$B$11,Inputs!$B$15*H4+Inputs!$B$16*H5) -> 1825
A16: M3 effective $/load | B16: =B15/B5 -> 1.0982659 | C16: =C15/C5 -> 0.7386836 | D16: =D15/D5 -> 0.7386836 | E16: =E15/E5 -> 0.83983051 | F16: =F15/F5 -> 0.7386836 | G16: =G15/G5 -> 0.7386836 | H16: =H15/H5 -> 0.60833333
A17: M3 gross margin | B17: =(B15-(B8+B6+B7)-(Inputs!$B$20*B15+Inputs!$B$21))/B15 -> 0.62321053 | C17: =(C15-(C8+C6+C7)-(Inputs!$B$20*C15+Inputs!$B$21))/C15 -> 0.56499531 | D17: =(D15-(D8+D6+D7)-(Inputs!$B$20*D15+Inputs!$B$21))/D15 -> 0.62205331 | E17: =(E15-(E8+E6+E7)-(Inputs!$B$20*E15+Inputs!$B$21))/E15 -> 0.43453582 | F17: =(F15-(F8+F6+F7)-(Inputs!$B$20*F15+Inputs!$B$21))/F15 -> 0.49996483 | G17: =(G15-(G8+G6+G7)-(Inputs!$B$20*G15+Inputs!$B$21))/G15 -> 0.4443919 | H17: =(H15-(H8+H6+H7)-(Inputs!$B$20*H15+Inputs!$B$21))/H15 -> 0.55017808
A18: Alvys-style reference @ $0.50/load (only the 3,000-load point is real) | B18: =B5*Inputs!$B$22 -> 8.65 | C18: =C5*Inputs!$B$22 -> 43.3 | D18: =D5*Inputs!$B$22 -> 86.6 | E18: =E5*Inputs!$B$22 -> 147.5 | F18: =F5*Inputs!$B$22 -> 216.5 | G18: =G5*Inputs!$B$22 -> 866 | H18: =H5*Inputs!$B$22 -> 1500
